lars/ECHO_INTEGRATION.md
lars/__init__.py
lars/agent.py
lars/alice_generator.py
lars/analytics_worker.py
lars/analyzer.py
lars/artifact_resolver.py
lars/auto_context.py
lars/azure_cost.py
lars/blocking_cost.py
lars/browser_manager.py
lars/caller_context.py
lars/cascade.py
lars/checkpoints.py
lars/cli.py
lars/confidence_worker.py
lars/config.py
lars/console_style.py
lars/content_classifier.py
lars/context_cards.py
lars/cost.py
lars/credits.py
lars/db_adapter.py
lars/demo_tools.py
lars/deterministic.py
lars/echo.py
lars/echo_enrichment.py
lars/echo_integration_example.py
lars/echoes.py
lars/elastic.py
lars/embedding_worker.py
lars/ephemeral_rag.py
lars/event_hooks.py
lars/extraction.py
lars/generative_ui.py
lars/generative_ui_schema.py
lars/harbor.py
lars/harbor_mgmt.py
lars/hotornot.py
lars/human_ui.py
lars/loaders.py
lars/logs.py
lars/mcp_cli.py
lars/mcp_client.py
lars/mcp_discovery.py
lars/memory.py
lars/mermaid_terminal.py
lars/model_metadata.py
lars/model_registry.py
lars/models_mgmt.py
lars/monitor.py
lars/pipeline_tools.py
lars/prompts.py
lars/reasoning.py
lars/research_cockpit.py
lars/runner.py
lars/schema.py
lars/screenshot_service.py
lars/session_naming.py
lars/session_registry.py
lars/session_state.py
lars/shadow_assessment.py
lars/signals.py
lars/skill_registry.py
lars/skills_manifest.py
lars/spec_validator.py
lars/sql_explain.py
lars/sql_rewriter.py
lars/sql_rewriter.py.backup
lars/sql_rewriter_messy.py
lars/sql_trail.py
lars/state.py
lars/terminal_image.py
lars/testing.py
lars/token_budget.py
lars/tool_cache.py
lars/tool_definitions.py
lars/tools_mgmt.py
lars/toon_transport.py
lars/toon_utils.py
lars/tracing.py
lars/training_system.py
lars/triggers.py
lars/unified_logs.py
lars/utils.py
lars/vertex_cost.py
lars/visual_compare.py
lars/visualizer.py
lars/voice.py
lars/watcher.py
lars/bi/__init__.py
lars/bi/metric_registry.py
lars/bi/understanding_store.py
lars/browser/__init__.py
lars/browser/artifacts.py
lars/browser/commands.py
larsql-2.4.0.dist-info/METADATA
larsql-2.4.0.dist-info/WHEEL
larsql-2.4.0.dist-info/entry_points.txt
larsql-2.4.0.dist-info/RECORD
