Metadata-Version: 2.4
Name: larsql
Version: 2.4.0
Summary: LARS: Declarative agent framework with first class SQL integration
Project-URL: Homepage, https://github.com/ryrobes/larsql
Project-URL: Repository, https://github.com/ryrobes/larsql
Project-URL: Documentation, https://larsql.com/
Author-email: Ryan Robitaille <ryan.robitaille@gmail.com>
License: OSASSY
Keywords: agents,declarative,llm,semantic,sql,workflows
Classifier: Development Status :: 4 - Beta
Classifier: Intended Audience :: Developers
Classifier: License :: OSI Approved
Classifier: Programming Language :: Python :: 3
Classifier: Programming Language :: Python :: 3.10
Classifier: Programming Language :: Python :: 3.11
Classifier: Programming Language :: Python :: 3.12
Classifier: Topic :: Scientific/Engineering :: Artificial Intelligence
Classifier: Topic :: Software Development :: Libraries :: Application Frameworks
Requires-Python: >=3.10
Requires-Dist: altair
Requires-Dist: chdb
Requires-Dist: clickhouse-connect
Requires-Dist: clickhouse-driver
Requires-Dist: duckdb
Requires-Dist: flask
Requires-Dist: flask-cors
Requires-Dist: gunicorn[gevent]
Requires-Dist: jinja2
Requires-Dist: jsonschema
Requires-Dist: kaleido
Requires-Dist: litellm
Requires-Dist: miniaudio
Requires-Dist: openpyxl
Requires-Dist: pandas
Requires-Dist: pillow
Requires-Dist: plotly
Requires-Dist: pyarrow
Requires-Dist: pydantic
Requires-Dist: pypdf
Requires-Dist: python-dotenv
Requires-Dist: readchar
Requires-Dist: requests
Requires-Dist: rich
Requires-Dist: ruamel-yaml
Requires-Dist: sqlglot
Requires-Dist: vl-convert-python
Provides-Extra: all
Requires-Dist: accelerate>=0.20.0; extra == 'all'
Requires-Dist: docker; extra == 'all'
Requires-Dist: fastapi>=0.100.0; extra == 'all'
Requires-Dist: httpx>=0.25.0; extra == 'all'
Requires-Dist: huggingface-hub<1.0,>=0.34.0; extra == 'all'
Requires-Dist: playwright>=1.40.0; extra == 'all'
Requires-Dist: torch>=2.0.0; extra == 'all'
Requires-Dist: transformers>=4.45.0; extra == 'all'
Requires-Dist: uvicorn[standard]>=0.23.0; extra == 'all'
Provides-Extra: browser
Requires-Dist: fastapi>=0.100.0; extra == 'browser'
Requires-Dist: httpx>=0.25.0; extra == 'browser'
Requires-Dist: playwright>=1.40.0; extra == 'browser'
Requires-Dist: uvicorn[standard]>=0.23.0; extra == 'browser'
Provides-Extra: docker
Requires-Dist: docker; extra == 'docker'
Provides-Extra: local-models
Requires-Dist: accelerate>=0.20.0; extra == 'local-models'
Requires-Dist: huggingface-hub<1.0,>=0.34.0; extra == 'local-models'
Requires-Dist: torch>=2.0.0; extra == 'local-models'
Requires-Dist: transformers>=4.45.0; extra == 'local-models'
